buildout.extensionscripts-1.1-py3.9-nspkg.pth
buildout/extensionscripts/__init__.py
buildout_extensionscripts-1.1.dist-info/METADATA
buildout_extensionscripts-1.1.dist-info/WHEEL
buildout_extensionscripts-1.1.dist-info/entry_points.txt
buildout_extensionscripts-1.1.dist-info/namespace_packages.txt
buildout_extensionscripts-1.1.dist-info/top_level.txt
buildout_extensionscripts-1.1.dist-info/RECORD
