Metadata-Version: 2.4
Name: buildout.extensionscripts
Version: 1.1
Summary: Use simple python scripts as zc.buildout extensions
License: BSD
Classifier: Programming Language :: Python
Classifier: Framework :: Buildout
Requires-Dist: setuptools
Dynamic: classifier
Dynamic: description
Dynamic: license
Dynamic: requires-dist
Dynamic: summary
